README.rst
setup.py
falcon_sslify/__init__.py
falcon_sslify.egg-info/PKG-INFO
falcon_sslify.egg-info/SOURCES.txt
falcon_sslify.egg-info/dependency_links.txt
falcon_sslify.egg-info/requires.txt
falcon_sslify.egg-info/top_level.txt