Metadata-Version: 1.0
Name: falcon-sslify
Version: 0.0.1
Summary: A middleware for falcon framework to force ssl onto to your app
Home-page: UNKNOWN
Author: Ritesh Kadmawala
Author-email: ritesh@loanzen.in
License: MIT
Platform: UNKNOWN
